google_ads_mcp/__init__.py
google_ads_mcp/client.py
google_ads_mcp/server.py
google_ads_mcp_rw-0.1.0.dist-info/METADATA
google_ads_mcp_rw-0.1.0.dist-info/WHEEL
google_ads_mcp_rw-0.1.0.dist-info/entry_points.txt
google_ads_mcp_rw-0.1.0.dist-info/licenses/LICENSE
google_ads_mcp_rw-0.1.0.dist-info/RECORD
