Metadata-Version: 2.4
Name: google-ads-mcp-rw
Version: 0.1.0
Summary: MCP server for Google Ads with read AND write capabilities
Project-URL: Homepage, https://github.com/MaxGhenis/google-ads-mcp-rw
Project-URL: Repository, https://github.com/MaxGhenis/google-ads-mcp-rw
Project-URL: Issues, https://github.com/MaxGhenis/google-ads-mcp-rw/issues
Author-email: Max Ghenis <max@policyengine.org>
License: MIT
License-File: LICENSE
Keywords: advertising,google-ads,mcp,model-context-protocol,ppc
Classifier: Development Status :: 4 - Beta
Classifier: Intended Audience :: Developers
Classifier: License :: OSI Approved :: MIT License
Classifier: Programming Language :: Python :: 3
Classifier: Programming Language :: Python :: 3.10
Classifier: Programming Language :: Python :: 3.11
Classifier: Programming Language :: Python :: 3.12
Classifier: Programming Language :: Python :: 3.13
Requires-Python: >=3.10
Requires-Dist: google-ads>=25.0.0
Requires-Dist: mcp[cli]>=1.6.0
Requires-Dist: pyyaml>=6.0
Provides-Extra: dev
Requires-Dist: black>=24.0.0; extra == 'dev'
Requires-Dist: pytest-asyncio>=0.23.0; extra == 'dev'
Requires-Dist: pytest>=8.0.0; extra == 'dev'
Requires-Dist: ruff>=0.3.0; extra == 'dev'
